tbthematic/__init__.py
tbthematic/commun_funcs.py
tbthematic/thematic.py
tbthematic-1.2.0.dist-info/METADATA
tbthematic-1.2.0.dist-info/WHEEL
tbthematic-1.2.0.dist-info/top_level.txt
tbthematic-1.2.0.dist-info/RECORD
