Metadata-Version: 2.1
Name: tbthematic
Version: 1.2.0
Summary: tbthematic
Home-page: UNKNOWN
Author: ZhiLin Zhang
License: MIT Licence
Keywords: pip,tbthematic
Platform: UNKNOWN
